.gitignore
.travis.yml
LICENSE
MANIFEST.in
README.rst
notebook5_constraints.txt
notebook6_constraints.txt
setup.cfg
setup.py
tox.ini
bin/pgcontents
examples/example_checkpoints_config.py
examples/example_jupyter_notebook_config.py
examples/hybrid_manager_example.py
pgcontents/__init__.py
pgcontents/alembic.ini
pgcontents/alembic.ini.template
pgcontents/api_utils.py
pgcontents/checkpoints.py
pgcontents/constants.py
pgcontents/crypto.py
pgcontents/db_utils.py
pgcontents/error.py
pgcontents/hybridmanager.py
pgcontents/managerbase.py
pgcontents/pgmanager.py
pgcontents/query.py
pgcontents/schema.py
pgcontents.egg-info/PKG-INFO
pgcontents.egg-info/SOURCES.txt
pgcontents.egg-info/dependency_links.txt
pgcontents.egg-info/not-zip-safe
pgcontents.egg-info/requires.txt
pgcontents.egg-info/top_level.txt
pgcontents/alembic/README
pgcontents/alembic/__init__.py
pgcontents/alembic/env.py
pgcontents/alembic/script.py.mako
pgcontents/alembic/versions/1217e5fbdbd9_.py
pgcontents/alembic/versions/2d46c89138b0_.py
pgcontents/alembic/versions/32518998055d_.py
pgcontents/alembic/versions/33b3645dc7f5_.py
pgcontents/alembic/versions/3d5ea85fc44f_.py
pgcontents/alembic/versions/551f95fbd4a2_.py
pgcontents/alembic/versions/597680fc6b80_.py
pgcontents/tests/__init__.py
pgcontents/tests/test_encryption.py
pgcontents/tests/test_hybrid_manager.py
pgcontents/tests/test_pgcontents_api.py
pgcontents/tests/test_pgmanager.py
pgcontents/tests/test_synchronization.py
pgcontents/tests/utils.py
pgcontents/utils/__init__.py
pgcontents/utils/ipycompat.py
pgcontents/utils/migrate.py
pgcontents/utils/sync.py