Metadata-Version: 2.1
Name: pgcontents
Version: 0.6
Summary: A Postgres-backed ContentsManager for IPython/Jupyter.
Home-page: https://github.com/quantopian/pgcontents
Author: Scott Sanderson
Author-email: ssanderson@quantopian.com
License: Apache 2.0
Platform: UNKNOWN
Classifier: Development Status :: 4 - Beta
Classifier: Framework :: IPython
Classifier: License :: OSI Approved :: Apache Software License
Classifier: Natural Language :: English
Classifier: Operating System :: OS Independent
Classifier: Programming Language :: Python :: 2.7
Classifier: Programming Language :: Python :: 3.5
Classifier: Programming Language :: Python :: 3.6
Classifier: Programming Language :: Python
Classifier: Topic :: Database
Provides-Extra: test
